svgfontembed/__init__.py
svgfontembed/svgfontembed.py
svgfontembed-0.1.1.dist-info/entry_points.txt
svgfontembed-0.1.1.dist-info/LICENSE
svgfontembed-0.1.1.dist-info/WHEEL
svgfontembed-0.1.1.dist-info/METADATA
svgfontembed-0.1.1.dist-info/RECORD
